LICENSE
README.md
setup.py
FE_workflow/AFE_analysis.py
FE_workflow/AFE_fesetup.py
FE_workflow/AFE_parameter.py
FE_workflow/RFE_analysis.py
FE_workflow/RFE_fesetup.py
FE_workflow/RFE_network.py
FE_workflow/RFE_parameter.py
FE_workflow/__init__.py
FE_workflow.egg-info/PKG-INFO
FE_workflow.egg-info/SOURCES.txt
FE_workflow.egg-info/dependency_links.txt
FE_workflow.egg-info/top_level.txt