Metadata-Version: 2.1
Name: FE_workflow
Version: 0.0.2
Summary: Free Energy workflow
Home-page: https://github.com/jnutyj/FreeEnergy_workflow
License: GNU General Public License v3.0
Keywords: python,free energy,gromacs
Classifier: Development Status :: 3 - Alpha
Classifier: Intended Audience :: Science/Research
Classifier: Topic :: Scientific/Engineering :: Chemistry
Classifier: Topic :: Scientific/Engineering :: Physics
Classifier: Programming Language :: Python :: 3
Classifier: Operating System :: OS Independent
Requires-Python: >=3.7, <4
License-File: LICENSE
